LICENSE
README.md
setup.py
pysvgedit/Convenience.py
pysvgedit/Exceptions.py
pysvgedit/SVGAnimation.py
pysvgedit/SVGCircle.py
pysvgedit/SVGDefs.py
pysvgedit/SVGDocument.py
pysvgedit/SVGGroup.py
pysvgedit/SVGImage.py
pysvgedit/SVGObject.py
pysvgedit/SVGPath.py
pysvgedit/SVGRect.py
pysvgedit/SVGStyle.py
pysvgedit/SVGText.py
pysvgedit/SVGTransformation.py
pysvgedit/SVGValidator.py
pysvgedit/Vector2D.py
pysvgedit/XMLTools.py
pysvgedit/__init__.py
pysvgedit.egg-info/PKG-INFO
pysvgedit.egg-info/SOURCES.txt
pysvgedit.egg-info/dependency_links.txt
pysvgedit.egg-info/entry_points.txt
pysvgedit.egg-info/top_level.txt
pysvgedit/apps/AnimationRendererApp.py
pysvgedit/apps/FriendlyArgumentParser.py
pysvgedit/apps/MakoRendererApp.py
pysvgedit/apps/ValidatorApp.py
pysvgedit/apps/__init__.py